{
  "indexes": [
    {
      "collectionGroup": "events",
      "queryScope": "COLLECTION",
      "fields": [
        { "fieldPath": "visible_in_game", "order": "ASCENDING" },
        { "fieldPath": "timestamp", "order": "ASCENDING" }
      ]
    },
    {
      "collectionGroup": "events",
      "queryScope": "COLLECTION",
      "fields": [
        { "fieldPath": "round", "order": "ASCENDING" },
        { "fieldPath": "timestamp", "order": "ASCENDING" }
      ]
    }
  ],
  "fieldOverrides": []
}
